{
  "display": {
    "icon": {
      "item": "industrialupgrade:itemingots",
      "data": 14
    },
    "title": {
      "translate": "advancement.silver_ingot"
    },
    "description": {
      "translate": "advancement.silver_ingot.desc"
    }
  },
  "parent": "industrialupgrade:basic_ores/silver_ore",
  "criteria": {
    "mine": {
      "trigger": "minecraft:inventory_changed",
      "conditions": {
        "items": [
          {
            "type": "forge:ore_dict",
            "ore": "ingotSilver"
          }
        ]
      }
    }
  }
}